hyperborea3/__init__.py
hyperborea3/chargen.py
hyperborea3/db.py
hyperborea3/hyperborea.sqlite3
hyperborea3/monsters.py
hyperborea3/namegen.py
hyperborea3/player_character.py
hyperborea3/py.typed
hyperborea3/spells.py
hyperborea3/valid_data.py
hyperborea3-0.6.0.dist-info/LICENSE
hyperborea3-0.6.0.dist-info/METADATA
hyperborea3-0.6.0.dist-info/WHEEL
hyperborea3-0.6.0.dist-info/top_level.txt
hyperborea3-0.6.0.dist-info/RECORD
