Metadata-Version: 2.1
Name: hyperborea3
Version: 0.6.0
Summary: Character Generator plus other tools for the Hyperborea RPG, 3rd Edition
Author: Jeremy Deram
License: MIT License
Project-URL: homepage, https://github.com/jderam/hyperborea3
Keywords: Dungeons,Dragons,Hyperborea,Hyperborea3,RPG
Classifier: Programming Language :: Python :: 3
Classifier: Programming Language :: Python :: 3 :: Only
Classifier: Programming Language :: Python :: 3.9
Classifier: Programming Language :: Python :: 3.10
Classifier: Programming Language :: Python :: 3.11
Classifier: License :: OSI Approved :: MIT License
Classifier: Operating System :: OS Independent
Requires-Python: >=3.9
License-File: LICENSE
Provides-Extra: dev
Requires-Dist: fastapi ; extra == 'dev'
Requires-Dist: ipython ; extra == 'dev'
Requires-Dist: pip-tools ; extra == 'dev'
Requires-Dist: pre-commit ; extra == 'dev'
Requires-Dist: twine ; extra == 'dev'
Requires-Dist: uvicorn ; extra == 'dev'
Provides-Extra: test
Requires-Dist: black ; extra == 'test'
Requires-Dist: flake8 ; extra == 'test'
Requires-Dist: tox ; extra == 'test'
Requires-Dist: pytest ; extra == 'test'
Requires-Dist: pytest-cov ; extra == 'test'
Requires-Dist: pytest-repeat ; extra == 'test'
Requires-Dist: mypy ; extra == 'test'
